<?xml version="1.0" encoding="UTF-8"?>
<cronentries>
	<cron>
		<url>/cron/team</url>
		<description>récupérations et mise à jour des équipes</description>
		<schedule>every week 02:30</schedule>
		<timezone>Europe/Paris</timezone>
	</cron>
	<cron>
		<url>/cron/schedule</url>
		<description>récupérations et mise à jour des rencontres</description>
		<schedule>every day 03:00</schedule>
		<timezone>Europe/Paris</timezone>
	</cron>
	<cron>
		<url>/cron/score</url>
		<description>récupérations et mise à jour des scores</description>
		<schedule>22 of month 03:30</schedule> <!-- every 10 minutes -->
		<timezone>Europe/Paris</timezone>
	</cron>
</cronentries>
